pycurl-stubs/METADATA.toml
pycurl-stubs/__init__.pyi
pycurl-stubs/py.typed
types_pycurl-7.45.7.20250926.dist-info/licenses/LICENSE
types_pycurl-7.45.7.20250926.dist-info/METADATA
types_pycurl-7.45.7.20250926.dist-info/WHEEL
types_pycurl-7.45.7.20250926.dist-info/top_level.txt
types_pycurl-7.45.7.20250926.dist-info/RECORD
